setup.py
dsnd_probability_ir_2020/Binomialdistribution.py
dsnd_probability_ir_2020/Gaussiandistribution.py
dsnd_probability_ir_2020/Generaldistribution.py
dsnd_probability_ir_2020/__init__.py
dsnd_probability_ir_2020.egg-info/PKG-INFO
dsnd_probability_ir_2020.egg-info/SOURCES.txt
dsnd_probability_ir_2020.egg-info/dependency_links.txt
dsnd_probability_ir_2020.egg-info/not-zip-safe
dsnd_probability_ir_2020.egg-info/top_level.txt