Metadata-Version: 1.0
Name: dsnd-probability-ir-2020
Version: 0.1
Summary: Gaussian distributions
Home-page: UNKNOWN
Author: Ibad Rather
Author-email: ibad.rather.ir@gmail.com
License: UNKNOWN
Platform: UNKNOWN
